[{"id":1738540800000,"name":"Lunes - Tren Inferior y Movilidad","date":"02/02/2026","data":[{"name":"Jumping Jacks","time":60,"type":"work"},{"name":"Sentadillas (Calentamiento)","time":90,"type":"work"},{"name":"Movilidad de cadera (Serie 1)","time":40,"type":"work"},{"name":"Movilidad de cadera (Serie 2)","time":40,"type":"work"},{"name":"Balanceo de pierna (Serie 1)","time":40,"type":"work"},{"name":"Balanceo de pierna (Serie 2)","time":40,"type":"work"},{"name":"Descanso","time":120,"type":"rest"},{"name":"Sentadilla completa (Serie 1)","time":60,"type":"work"},{"name":"Descanso","time":120,"type":"rest"},{"name":"Sentadilla completa (Serie 2)","time":60,"type":"work"},{"name":"Descanso","time":120,"type":"rest"},{"name":"Sentadilla completa (Serie 3)","time":60,"type":"work"},{"name":"Descanso","time":120,"type":"rest"},{"name":"Sentadilla completa (Serie 4)","time":60,"type":"work"},{"name":"Descanso","time":120,"type":"rest"},{"name":"Zancadas (Serie 1)","time":60,"type":"work"},{"name":"Descanso","time":120,"type":"rest"},{"name":"Zancadas (Serie 2)","time":60,"type":"work"},{"name":"Descanso","time":120,"type":"rest"},{"name":"Zancadas (Serie 3)","time":60,"type":"work"},{"name":"Descanso","time":120,"type":"rest"},{"name":"Sentadilla isométrica en pared (Serie 1)","time":45,"type":"work"},{"name":"Descanso","time":120,"type":"rest"},{"name":"Sentadilla isométrica en pared (Serie 2)","time":45,"type":"work"},{"name":"Descanso","time":120,"type":"rest"},{"name":"Sentadilla isométrica en pared (Serie 3)","time":45,"type":"work"},{"name":"Descanso","time":120,"type":"rest"},{"name":"Puente a una pierna (L+R - Bloque 1)","time":60,"type":"work"},{"name":"Descanso","time":120,"type":"rest"},{"name":"Puente a una pierna (L+R - Bloque 2)","time":60,"type":"work"},{"name":"Descanso","time":120,"type":"rest"},{"name":"Puente a una pierna (L+R - Bloque 3)","time":60,"type":"work"},{"name":"Descanso","time":120,"type":"rest"},{"name":"Elevaciones talón 1p (L+R - Bloque 1)","time":80,"type":"work"},{"name":"Descanso","time":120,"type":"rest"},{"name":"Elevaciones talón 1p (L+R - Bloque 2)","time":80,"type":"work"},{"name":"Descanso","time":120,"type":"rest"},{"name":"Elevaciones talón 1p (L+R - Bloque 3)","time":80,"type":"work"},{"name":"Estiramiento Final","time":395,"type":"work"}]},{"id":1738627200000,"name":"Martes - Empuje (Tren Superior)","date":"03/02/2026","data":[{"name":"Rotaciones de hombros (Serie 1)","time":30,"type":"work"},{"name":"Rotaciones de hombros (Serie 2)","time":30,"type":"work"},{"name":"Círculo brazos extendidos (Serie 1)","time":20,"type":"work"},{"name":"Círculo brazos extendidos (Serie 2)","time":20,"type":"work"},{"name":"Flexiones en pared","time":40,"type":"work"},{"name":"Descanso","time":60,"type":"rest"},{"name":"Flexiones en pared","time":40,"type":"work"},{"name":"Descanso","time":60,"type":"rest"},{"name":"Plancha inclinada","time":30,"type":"work"},{"name":"Descanso","time":60,"type":"rest"},{"name":"Plancha inclinada","time":30,"type":"work"},{"name":"Descanso","time":120,"type":"rest"},{"name":"Flexiones inclinadas (Serie 1)","time":40,"type":"work"},{"name":"Descanso","time":120,"type":"rest"},{"name":"Flexiones inclinadas (Serie 2)","time":40,"type":"work"},{"name":"Descanso","time":120,"type":"rest"},{"name":"Flexiones inclinadas (Serie 3)","time":40,"type":"work"},{"name":"Descanso","time":120,"type":"rest"},{"name":"Flexiones inclinadas (Serie 4)","time":40,"type":"work"},{"name":"Descanso","time":120,"type":"rest"},{"name":"Fondos en silla (Serie 1)","time":40,"type":"work"},{"name":"Descanso","time":120,"type":"rest"},{"name":"Fondos en silla (Serie 2)","time":40,"type":"work"},{"name":"Descanso","time":120,"type":"rest"},{"name":"Fondos en silla (Serie 3)","time":40,"type":"work"},{"name":"Descanso","time":120,"type":"rest"},{"name":"Fondos en silla (Serie 4)","time":40,"type":"work"},{"name":"Descanso","time":120,"type":"rest"},{"name":"Flexiones pica (Serie 1)","time":30,"type":"work"},{"name":"Descanso","time":120,"type":"rest"},{"name":"Flexiones pica (Serie 2)","time":30,"type":"work"},{"name":"Descanso","time":120,"type":"rest"},{"name":"Flexiones pica (Serie 3)","time":30,"type":"work"},{"name":"Descanso","time":120,"type":"rest"},{"name":"Plancha toque hombros (Serie 1)","time":30,"type":"work"},{"name":"Descanso","time":120,"type":"rest"},{"name":"Plancha toque hombros (Serie 2)","time":30,"type":"work"},{"name":"Descanso","time":120,"type":"rest"},{"name":"Plancha toque hombros (Serie 3)","time":30,"type":"work"},{"name":"Descanso","time":120,"type":"rest"},{"name":"Empujar la pared (Isométrico 1)","time":40,"type":"work"},{"name":"Descanso","time":120,"type":"rest"},{"name":"Empujar la pared (Isométrico 2)","time":40,"type":"work"}]},{"id":1738713600000,"name":"Miércoles - Core y Estabilidad","date":"04/02/2026","data":[{"name":"Respiración profunda","time":130,"type":"work"},{"name":"Gato-vaca","time":60,"type":"work"},{"name":"Puentes de glúteo","time":60,"type":"work"},{"name":"Pájaro-perro (Calentamiento)","time":70,"type":"work"},{"name":"Descanso","time":120,"type":"rest"},{"name":"Plancha frontal (Serie 1)","time":40,"type":"work"},{"name":"Descanso","time":120,"type":"rest"},{"name":"Plancha frontal (Serie 2)","time":40,"type":"work"},{"name":"Descanso","time":120,"type":"rest"},{"name":"Plancha frontal (Serie 3)","time":40,"type":"work"},{"name":"Descanso","time":120,"type":"rest"},{"name":"Plancha frontal (Serie 4)","time":40,"type":"work"},{"name":"Descanso","time":120,"type":"rest"},{"name":"Dead bug (Serie 1)","time":80,"type":"work"},{"name":"Descanso","time":120,"type":"rest"},{"name":"Dead bug (Serie 2)","time":80,"type":"work"},{"name":"Descanso","time":120,"type":"rest"},{"name":"Dead bug (Serie 3)","time":80,"type":"work"},{"name":"Descanso","time":120,"type":"rest"},{"name":"Bird dog (Serie 1)","time":80,"type":"work"},{"name":"Descanso","time":120,"type":"rest"},{"name":"Bird dog (Serie 2)","time":80,"type":"work"},{"name":"Descanso","time":120,"type":"rest"},{"name":"Bird dog (Serie 3)","time":80,"type":"work"},{"name":"Descanso","time":120,"type":"rest"},{"name":"Cuchara / Hollow Hold (Serie 1)","time":30,"type":"work"},{"name":"Descanso","time":120,"type":"rest"},{"name":"Cuchara / Hollow Hold (Serie 2)","time":30,"type":"work"},{"name":"Descanso","time":120,"type":"rest"},{"name":"Cuchara / Hollow Hold (Serie 3)","time":30,"type":"work"},{"name":"Descanso","time":120,"type":"rest"},{"name":"Superman (Serie 1)","time":20,"type":"work"},{"name":"Descanso","time":120,"type":"rest"},{"name":"Superman (Serie 2)","time":20,"type":"work"},{"name":"Descanso","time":120,"type":"rest"},{"name":"Superman (Serie 3)","time":20,"type":"work"}]},{"id":1738785600000,"name":"Jueves - Pierna y Movilidad","date":"05/02/2026","data":[{"name":"Marcha lateral + desplazamientos","time":120,"type":"work"},{"name":"Movilidad de tobillos","time":20,"type":"work"},{"name":"Sentadilla + elevación de brazos","time":40,"type":"work"},{"name":"Descanso","time":60,"type":"rest"},{"name":"Sentadilla + elevación de brazos","time":40,"type":"work"},{"name":"Descanso","time":60,"type":"rest"},{"name":"Peso muerto a una pierna","time":30,"type":"work"},{"name":"Descanso","time":20,"type":"rest"},{"name":"Peso muerto a una pierna (otra pierna)","time":30,"type":"work"},{"name":"Descanso","time":20,"type":"rest"},{"name":"Sentadilla lenta (Serie 1)","time":50,"type":"work"},{"name":"Descanso","time":120,"type":"rest"},{"name":"Sentadilla lenta (Serie 2)","time":50,"type":"work"},{"name":"Descanso","time":120,"type":"rest"},{"name":"Sentadilla lenta (Serie 3)","time":50,"type":"work"},{"name":"Descanso","time":120,"type":"rest"},{"name":"Sentadilla lenta (Serie 4)","time":50,"type":"work"},{"name":"Descanso","time":120,"type":"rest"},{"name":"Zancada atrás (Serie 1)","time":50,"type":"work"},{"name":"Descanso","time":120,"type":"rest"},{"name":"Zancada atrás (Serie 2)","time":50,"type":"work"},{"name":"Descanso","time":120,"type":"rest"},{"name":"Zancada atrás (Serie 3)","time":50,"type":"work"},{"name":"Descanso","time":120,"type":"rest"},{"name":"Cañón asistido (Serie 1)","time":30,"type":"work"},{"name":"Descanso","time":60,"type":"rest"},{"name":"Cañón asistido (Serie 2)","time":30,"type":"work"},{"name":"Descanso","time":60,"type":"rest"},{"name":"Cañón asistido (Serie 3)","time":30,"type":"work"},{"name":"Descanso","time":60,"type":"rest"},{"name":"Cañón asistido (Serie 4)","time":30,"type":"work"},{"name":"Descanso","time":60,"type":"rest"},{"name":"Cañón asistido (Serie 5)","time":30,"type":"work"},{"name":"Descanso","time":60,"type":"rest"},{"name":"Cañón asistido (Serie 6)","time":30,"type":"work"},{"name":"Descanso","time":120,"type":"rest"},{"name":"Peso muerto a una pierna (L+R)","time":60,"type":"work"},{"name":"Descanso","time":120,"type":"rest"},{"name":"Peso muerto a una pierna (L+R)","time":60,"type":"work"},{"name":"Descanso","time":120,"type":"rest"},{"name":"Peso muerto a una pierna (L+R)","time":60,"type":"work"}]},{"id":1770034814143,"name":"Viernes - Rutina Movilidad y Torso","date":"5/2/2026","data":[{"name":"Movilidad hombros y cuello","time":120,"type":"work"},{"name":"Círculos amplios brazos","time":80,"type":"work"},{"name":"Flexiones inclinadas","time":40,"type":"work"},{"name":"Descanso","time":60,"type":"rest"},{"name":"Flexiones inclinadas","time":40,"type":"work"},{"name":"Descanso","time":60,"type":"rest"},{"name":"Plancha corta","time":20,"type":"work"},{"name":"Descanso","time":60,"type":"rest"},{"name":"Plancha corta","time":20,"type":"work"},{"name":"Descanso","time":60,"type":"rest"},{"name":"Flexiones inclinadas","time":60,"type":"work"},{"name":"Descanso","time":120,"type":"rest"},{"name":"Flexiones inclinadas","time":60,"type":"work"},{"name":"Descanso","time":120,"type":"rest"},{"name":"Flexiones inclinadas","time":60,"type":"work"},{"name":"Descanso","time":120,"type":"rest"},{"name":"Elevaciones frontales con goma","time":30,"type":"work"},{"name":"Descanso","time":120,"type":"rest"},{"name":"Elevaciones frontales con goma","time":30,"type":"work"},{"name":"Descanso","time":120,"type":"rest"},{"name":"Elevaciones frontales con goma","time":30,"type":"work"},{"name":"Descanso","time":120,"type":"rest"},{"name":"Plancha lateral","time":30,"type":"work"},{"name":"Descanso","time":90,"type":"rest"},{"name":"Plancha lateral","time":30,"type":"work"},{"name":"Descanso","time":90,"type":"rest"},{"name":"Plancha lateral","time":30,"type":"work"},{"name":"Descanso","time":90,"type":"rest"},{"name":"Plancha lateral","time":30,"type":"work"},{"name":"Descanso","time":90,"type":"rest"},{"name":"Plancha lateral","time":30,"type":"work"},{"name":"Descanso","time":90,"type":"rest"},{"name":"Plancha lateral","time":30,"type":"work"},{"name":"Descanso","time":90,"type":"rest"},{"name":"Cuchara","time":40,"type":"work"},{"name":"Descanso","time":120,"type":"rest"},{"name":"Cuchara","time":40,"type":"work"},{"name":"Descanso","time":120,"type":"rest"},{"name":"Cuchara","time":40,"type":"work"},{"name":"Descanso","time":120,"type":"rest"}]}]